setupext_pip-1.1.0-py2.7-nspkg.pth
setupext/pip.py
setupext_pip-1.1.0.dist-info/LICENSE
setupext_pip-1.1.0.dist-info/METADATA
setupext_pip-1.1.0.dist-info/WHEEL
setupext_pip-1.1.0.dist-info/entry_points.txt
setupext_pip-1.1.0.dist-info/namespace_packages.txt
setupext_pip-1.1.0.dist-info/top_level.txt
setupext_pip-1.1.0.dist-info/RECORD
