Metadata-Version: 2.1
Name: setupext-pip
Version: 1.1.0
Summary: Setuptools extension for installing requirements
Home-page: http://github.com/dave-shawley/setupext-pip
Author: Dave Shawley
Author-email: daveshawley@gmail.com
License: UNKNOWN
Platform: any
Classifier: Intended Audience :: Developers
Classifier: License :: OSI Approved :: BSD License
Classifier: Operating System :: OS Independent
Classifier: Programming Language :: Python
Classifier: Programming Language :: Python :: 2
Classifier: Programming Language :: Python :: 2.7
Classifier: Programming Language :: Python :: 3
Classifier: Programming Language :: Python :: 3.4
Classifier: Programming Language :: Python :: 3.5
Classifier: Programming Language :: Python :: 3.6
Classifier: Programming Language :: Python :: 3.7
Classifier: Programming Language :: Python :: 3.8
Classifier: Framework :: Setuptools Plugin
Classifier: Development Status :: 4 - Beta
Requires-Dist: pip (>=1.5)
